cloud_conformity/__init__.py
cloud_conformity/cloud_conformity.py
cloud_conformity-1.0.3.dist-info/LICENSE
cloud_conformity-1.0.3.dist-info/METADATA
cloud_conformity-1.0.3.dist-info/WHEEL
cloud_conformity-1.0.3.dist-info/top_level.txt
cloud_conformity-1.0.3.dist-info/RECORD
