Metadata-Version: 2.1
Name: cloud-conformity
Version: 1.0.3
Summary: Python library to interact with Cloud Conformity API
Home-page: https://github.com/traveloka/cloud-conformity-python-library
Author: Rafi Kurnia Putra
Author-email: rafi.putra@traveloka.com
License: Apache License 2.0
Platform: UNKNOWN
Requires-Python: >=3
Requires-Dist: requests (==2.23.0)
